starlette_msgspec/__init__.py
starlette_msgspec/openapi.py
starlette_msgspec/router.py
starlette_msgspec-0.6.0.dist-info/licenses/LICENSE
starlette_msgspec-0.6.0.dist-info/METADATA
starlette_msgspec-0.6.0.dist-info/WHEEL
starlette_msgspec-0.6.0.dist-info/top_level.txt
starlette_msgspec-0.6.0.dist-info/RECORD
