Metadata-Version: 2.4
Name: starlette-msgspec
Version: 0.6.0
Summary: FastAPI-like router for Starlette with msgspec integration
License: MIT
Requires-Python: >=3.8
License-File: LICENSE
Requires-Dist: starlette>=0.28.0
Requires-Dist: msgspec>=0.18.0
Provides-Extra: test
Requires-Dist: pytest>=7.0.0; extra == "test"
Requires-Dist: pytest-asyncio>=0.18.0; extra == "test"
Requires-Dist: httpx>=0.24.0; extra == "test"
Dynamic: license-file
